README
setup.cfg
setup.py
traceb.py
traceb.egg-info/PKG-INFO
traceb.egg-info/SOURCES.txt
traceb.egg-info/dependency_links.txt
traceb.egg-info/top_level.txt