Metadata-Version: 1.1
Name: traceb
Version: 0.1.1
Summary: traceback with verbose and compact options
Home-page: http://github.com/tiagocoutinho/traceb
Author: Tiago Coutinho
Author-email: coutinhotiago@gmail.com
License: MIT
Platform: any
Classifier: Development Status :: 4 - Beta
Classifier: Intended Audience :: Developers
Classifier: License :: OSI Approved :: MIT License
Classifier: Programming Language :: Python :: 2.6
Classifier: Programming Language :: Python :: 2.7
Classifier: Programming Language :: Python :: 3
Classifier: Programming Language :: Python :: 3.2
Classifier: Programming Language :: Python :: 3.3
Classifier: Programming Language :: Python :: 3.4
Classifier: Programming Language :: Python :: 3.5
